{
  "name": "Aster",
  "slug": "aster",
  "galleryOrder": 91,
  "description": "Six-armed thread stars twirling lazily across the canvas — every redraw spins each one to a new resting angle.",
  "palette": [
    "#FFF8F2",
    "#FF7E9D",
    "#FFB35C",
    "#9D89F2",
    "#54C6B8"
  ],
  "colors": {
    "min": 2,
    "max": 5,
    "default": 5
  },
  "options": [
    {
      "id": "grid",
      "displayName": "Columns and rows",
      "type": "ButtonSelectGroup",
      "default": "8x12",
      "options": [
        "2x3",
        "4x6",
        "6x9",
        "8x12",
        "10x15"
      ],
      "replace": "${grid}"
    },
    {
      "id": "frequency",
      "displayName": "Frequency",
      "type": "Slider",
      "default": 0.9,
      "min": 0.2,
      "max": 1,
      "step": 0.1,
      "replace": "${shapeFrequency}"
    },
    {
      "id": "thickness",
      "displayName": "Thickness",
      "type": "Slider",
      "default": 1,
      "min": 0.5,
      "max": 4,
      "step": 0.1,
      "replace": "${thickness}"
    }
  ],
  "code": {
    "style": "--spin: @rand(180deg); --rule: ( /* all three arms share one emitted color; thickness scales each arm along its own thin axis. The pseudo arms inherit the parent's scaleY, so they undo it before rotating to avoid shearing. */ --star: @p(var(--color1), var(--color2), var(--color3), var(--color4)); @random(${shapeFrequency}) { width: 72%; height: 2.6%; margin: 48.7% 14%; border-radius: 99px; background: @var(--star); transform: rotate(var(--spin)) scaleY(${thickness}); :before { content: ''; position: absolute; inset: 0; border-radius: 99px; background: @var(--star); transform: scaleY(calc(1 / ${thickness})) rotate(60deg) scaleY(${thickness}); } :after { content: ''; position: absolute; inset: 0; border-radius: 99px; background: @var(--star); transform: scaleY(calc(1 / ${thickness})) rotate(120deg) scaleY(${thickness}); } } transition: ease 600ms; );",
    "doodle": ":doodle { @grid: ${grid}; @size: ${width} ${height}; overflow:hidden; text-align:center; box-sizing:border-box } :container { background: var(--color0); overflow:hidden; }"
  }
}
